nvalchemiops/__init__.py
nvalchemiops/autograd.py
nvalchemiops/spline.py
nvalchemiops/types.py
nvalchemiops/interactions/__init__.py
nvalchemiops/interactions/dispersion/__init__.py
nvalchemiops/interactions/dispersion/dftd3.py
nvalchemiops/interactions/electrostatics/__init__.py
nvalchemiops/interactions/electrostatics/coulomb.py
nvalchemiops/interactions/electrostatics/ewald.py
nvalchemiops/interactions/electrostatics/ewald_kernels.py
nvalchemiops/interactions/electrostatics/k_vectors.py
nvalchemiops/interactions/electrostatics/parameters.py
nvalchemiops/interactions/electrostatics/pme.py
nvalchemiops/interactions/electrostatics/pme_kernels.py
nvalchemiops/math/__init__.py
nvalchemiops/math/gto.py
nvalchemiops/math/math.py
nvalchemiops/math/spherical_harmonics.py
nvalchemiops/neighborlist/__init__.py
nvalchemiops/neighborlist/batch_cell_list.py
nvalchemiops/neighborlist/batch_naive.py
nvalchemiops/neighborlist/batch_naive_dual_cutoff.py
nvalchemiops/neighborlist/cell_list.py
nvalchemiops/neighborlist/naive.py
nvalchemiops/neighborlist/naive_dual_cutoff.py
nvalchemiops/neighborlist/neighbor_utils.py
nvalchemiops/neighborlist/neighborlist.py
nvalchemiops/neighborlist/rebuild_detection.py
nvalchemi_toolkit_ops-0.2.0.dist-info/METADATA
nvalchemi_toolkit_ops-0.2.0.dist-info/WHEEL
nvalchemi_toolkit_ops-0.2.0.dist-info/licenses/LICENSE
nvalchemi_toolkit_ops-0.2.0.dist-info/RECORD
