Metadata-Version: 2.4
Name: nvalchemi-toolkit-ops
Version: 0.2.0
Summary: High-performance NVIDIA Warp primitives for GPU-enabled computational chemistry and atomistic simulation workflows.
Author: nvalchemiops Team
License-Expression: Apache-2.0
License-File: LICENSE
Keywords: atomic simulation,batched operations,computational chemistry,cuda,gpu,molecular dynamics,neighborlist,nvidia-warp,optimization
Classifier: Environment :: GPU
Classifier: Intended Audience :: Science/Research
Classifier: License :: OSI Approved :: Apache Software License
Classifier: Operating System :: OS Independent
Classifier: Programming Language :: Python :: 3
Classifier: Topic :: Scientific/Engineering :: Chemistry
Classifier: Topic :: Scientific/Engineering :: Physics
Requires-Python: >=3.11
Requires-Dist: numpy
Requires-Dist: torch>=2.8.0
Requires-Dist: warp-lang>=1.10.0
